env/bin/jp.py
userhub/__init__.py
userhub/auth.py
userhub/model.py
userhub-0.18.dist-info/licenses/LICENSE
userhub-0.18.dist-info/METADATA
userhub-0.18.dist-info/WHEEL
userhub-0.18.dist-info/top_level.txt
userhub-0.18.dist-info/RECORD
