Metadata-Version: 2.4
Name: userhub
Version: 0.18
Summary: User Authorization System
Home-page: https://github.com/chilleco/userhub
Author: Alex Poloz
Author-email: Alex Poloz <alexypoloz@gmail.com>
License: MIT License
Project-URL: Homepage, https://github.com/chilleco/userhub
Project-URL: Source, https://github.com/chilleco/userhub
Project-URL: PyPI, https://pypi.org/project/userhub/
Keywords: auth,auth system,auth hub,user authenticator,authentication system
Classifier: Development Status :: 4 - Beta
Classifier: Environment :: Console
Classifier: Intended Audience :: Developers
Classifier: Topic :: Software Development :: Libraries :: Application Frameworks
Classifier: License :: OSI Approved :: MIT License
Classifier: Programming Language :: Python :: 3
Classifier: Programming Language :: Python :: 3 :: Only
Classifier: Programming Language :: Python :: 3.8
Classifier: Programming Language :: Python :: 3.9
Classifier: Programming Language :: Python :: 3.10
Classifier: Programming Language :: Python :: 3.11
Classifier: Programming Language :: Python :: 3.12
Classifier: Programming Language :: Python :: 3.13
Classifier: Operating System :: OS Independent
Requires-Python: >=3.8, <4
License-File: LICENSE
Requires-Dist: libdev>=0.97
Requires-Dist: consys>=0.44
Provides-Extra: dev
Requires-Dist: twine>=6.2.0; extra == "dev"
Requires-Dist: setuptools>=80.9.0; extra == "dev"
Requires-Dist: build>=1.2.1; extra == "dev"
Dynamic: author
Dynamic: home-page
Dynamic: license-file
Dynamic: requires-python
